src/fixedPt.vhd
library ieee;
use ieee.std_logic_1164.all;
use ieee.numeric_std.all;

package fixedPt is
    component FPP_ADD is
        port(
            A   :   in std_logic_vector(31 downto 0);
            B   :   in std_logic_vector(31 downto 0);
            sel :   in std_logic;
            result  :   out std_logic_vector(31 downto 0)
        );
    end component;
    
    component FPP_SUB is
        port(
            A   :   in std_logic_vector(31 downto 0);
            B   :   in std_logic_vector(31 downto 0);
            sel :   in std_logic;
            result  :   out std_logic_vector(31 downto 0)
        );
    end component;

    component FPP_MUL is
        generic(SCALE : integer := 28);
        port(
            A   :   in std_logic_vector(31 downto 0);
            B   :   in std_logic_vector(31 downto 0);
            sel :   in std_logic;
            result  :   out std_logic_vector(31 downto 0)
        );
    end component;

    component FPP_DIV is
        generic(SCALE : integer := 28);
        port(
            A   :   in std_logic_vector(31 downto 0);
            B   :   in std_logic_vector(31 downto 0);
            sel :   in std_logic;
            result  :   out std_logic_vector(63 downto 0)
        );
    end component;
end package fixedPt;

library ieee;
use ieee.std_logic_1164.all;
use ieee.numeric_std.all;

entity FPP_ADD is
    port(
        A   :   in std_logic_vector(31 downto 0);
        B   :   in std_logic_vector(31 downto 0);
        sel :   in std_logic;
        result  :   out std_logic_vector(31 downto 0)
    );
end FPP_ADD;

architecture behavior of FPP_ADD is
signal t_result :   std_logic_vector(31 downto 0);
begin
    t_result <= std_logic_vector( signed(A) + signed(B)) when (sel = '0') else
        (others => 'Z');
    result <= t_result when (sel = '0') else
        (others => 'Z');
end behavior;

library ieee;
use ieee.std_logic_1164.all;
use ieee.numeric_std.all;

entity FPP_SUB is
    port(
        A   :   in std_logic_vector(31 downto 0);
        B   :   in std_logic_vector(31 downto 0);
        sel :   in std_logic;
        result  :   out std_logic_vector(31 downto 0)
    );
end FPP_SUB;

architecture behavior of FPP_SUB is
signal t_result : std_logic_vector(31 downto 0);
begin
    t_result <= std_logic_vector( unsigned(A) - unsigned(B) ) when ( sel = '0' ) else
        (others => 'Z');
    result <= t_result when (sel = '0') else 
        (others => 'Z');
end behavior;

library ieee;
use ieee.std_logic_1164.all;
use ieee.numeric_std.all;

entity FPP_MUL is
    generic ( SCALE : integer := 28 );
    port(
        A   :   in std_logic_vector(31 downto 0);
        B   :   in std_logic_vector(31 downto 0);
        sel :   in std_logic;
        result  :   out std_logic_vector(31 downto 0)
    );
end FPP_MUL;

architecture behavior of FPP_MUL is
signal t_result, t_mul : std_logic_vector(63 downto 0);
begin
    t_mul <= std_logic_vector( unsigned(A) * unsigned(B) ) when (sel = '0' ) else 
        (others=>'Z');
    t_result <= std_logic_vector( shift_right( unsigned(t_mul), SCALE ) ) when (sel = '0') else
        (others=>'Z'); 
    result <= t_result(31 downto 0) when (sel = '0') else
        (others=>'Z');
end behavior;

library ieee;
use ieee.std_logic_1164.all;
use ieee.numeric_std.all;

entity FPP_DIV is
    generic ( SCALE : integer := 28 );
    port(
        A   :   in std_logic_vector(31 downto 0);
        B   :   in std_logic_vector(31 downto 0);
        sel :   in std_logic;
        result  :   out std_logic_vector(31 downto 0)
    );
end FPP_DIV;

architecture behavior of FPP_DIV is
signal t_A : std_logic_vector(63 downto 0);
signal t_B : std_logic_vector(63 downto 0);
signal t_div, t_result : std_logic_vector(63 downto 0);
begin
    t_A <= "0000" & A & X"0000000" when (sel = '0') else 
        (others => 'Z');
    t_B <= X"00000000" & B when (sel = '0') else 
        (others => 'Z');
    t_div <= std_logic_vector( unsigned(t_A) / unsigned(t_B) ) when (sel = '0') else
        (others=>'Z');
    result <= t_div(31 downto 0) when (sel = '0') else
        (others => 'Z');
end behavior;

src/FPU.vhd
----------------------------------------------------------------
-- FPU.vhd is Fixed point unit
----------------------------------------------------------------

library ieee;
use IEEE.std_logic_1164.all;
use IEEE.numeric_std.all;
use work.fixedPt.all;

entity FPU is
    port(
        A, B    : in std_logic_vector(31 downto 0);
        op      : in std_logic_vector(1 downto 0);
        result  : out std_logic_vector(31 downto 0)
    );
end FPU;

architecture behavior of FPU is
    component FPP_ADD is
        port(
            A   : in std_logic_vector(31 downto 0);
            B   : in std_logic_vector(31 downto 0);
            sel : in std_logic;
            result  : out std_logic_vector(31 downto 0)
        );
    end component;

    component FPP_SUB is
        port(
            A   : in std_logic_vector(31 downto 0);
            B   : in std_logic_vector(31 downto 0);
            sel : in std_logic;
            result  : out std_logic_vector(31 downto 0)
        );
    end component;

    component FPP_MUL is
        generic ( SCALE : integer := 28 );
        port(
            A   : in std_logic_vector(31 downto 0);
            B   : in std_logic_vector(31 downto 0);
            sel : in std_logic;
            result  : out std_logic_vector(31 downto 0)
        );
    end component;

    component FPP_DIV is
        generic ( SCALE : integer := 28 );
        port(
            A   : in std_logic_vector(31 downto 0);
            B   : in std_logic_vector(31 downto 0);
            sel : in std_logic;
            result  : out std_logic_vector(31 downto 0)
        );
    end component;
    
signal t_A, t_B : std_logic_vector(31 downto 0);
signal t_result_add : std_logic_vector(31 downto 0);
signal t_result_sub : std_logic_vector(31 downto 0);
signal t_result_div : std_logic_vector(31 downto 0);
signal t_result_mul : std_logic_vector(31 downto 0);
signal t_sel : std_logic_vector(3 downto 0);
begin
    t_A <= A;
    t_B <= B;

    t_sel(0) <= op(0) or op(1);
    t_sel(1) <= not op(0) or op(1);
    t_sel(2) <= op(0) or not op(1);
    t_sel(3) <= not op(0) or not op(1);

    add : FPP_ADD
        port map(
            A => t_A,
            B => t_B,
            sel => t_sel(0),
            result => t_result_add
        );
    sub : FPP_SUB
        port map(
            A => t_A,
            B => t_B,
            sel => t_sel(1),
            result => t_result_sub
        );
    mul : FPP_MUL
        port map(
            A => t_A,
            B => t_B,
            sel => t_sel(2),
            result => t_result_mul
        );
    div : FPP_DIV
        port map(
            A => t_A,
            B => t_B,
            sel => t_sel(3),
            result => t_result_div
        );
    result <= t_result_add when t_sel = "1110" else
        t_result_sub when t_sel = "1101" else
        t_result_mul when t_sel = "1011" else
        t_result_div when t_sel = "0111" else 
        (others => 'Z'); 
end behavior;

src/D_FF.vhd
library ieee;
use ieee.std_logic_1164.all;

entity D_FF is
    port(
        D   :   in std_logic_vector(31 downto 0);
        enable: in std_logic;
        clk :   in std_logic;
        Q   :   out std_logic_vector(31 downto 0)
    );
end D_FF;

architecture behavior of D_FF is
signal Q_out, D_in  : std_logic_vector(31 downto 0);
signal enable_32bit : std_logic_vector(31 downto 0);
begin
    enable_32bit <= (others => enable);
    D_in <= (D and enable_32bit) or (Q_out and not(enable_32bit));
    process(D_in, enable_32bit, clk)
    begin
        if rising_edge(clk) then Q_out <= D_in; end if;
    end process;
    Q <= Q_out;
end behavior;

src/Core.vhd
library ieee;
use IEEE.std_logic_1164.all;
use IEEE.numeric_std.all;
use work.fixedPt.all;

entity Core is
    port(
        dataIn : in std_logic_vector(63 downto 0);
        clk : in std_logic;
        load : in std_logic;
        op : in std_logic_vector(1 downto 0);
        dataOut : out std_logic_vector(31 downto 0);
        isDone : out std_logic
    );
end Core;

architecture behavior of Core is
    component FPU is
        port(
            A   : in std_logic_vector(31 downto 0);
            B   : in std_logic_vector(31 downto 0);
            op  : in std_logic_vector(1 downto 0);
            result : out std_logic_vector(31 downto 0)
        );
    end component;
    component D_FF is
        port(
            D   : in std_logic_vector(31 downto 0);
            clk : in std_logic;
            enable : in std_logic;
            Q : out std_logic_vector(31 downto 0)
        );
    end component;
signal t_A, t_B : std_logic_vector(31 downto 0);
signal t_R : std_logic_vector(31 downto 0);
signal Q_A, Q_B, Q_R : std_logic_vector(31 downto 0);
signal t_done : std_logic := '0';
begin
    t_A <= dataIn(31 downto 0);
    t_B <= dataIn(63 downto 32);
    isDone <= t_done;
    dataOut <= t_R;
    DFF_A : D_FF
        port map(
            D => t_A,
            clk => clk,
            enable => load,
            Q => Q_A
        );
    DFF_B : D_FF
        port map(
            D => t_B,
            clk => clk,
            enable => load,
            Q => Q_B
        );
    DFF_R : D_FF
        port map(
            D => t_R,
            clk => clk,
            enable => load,
            Q => Q_R
        );

    FPUcore : FPU
        port map(
            A => Q_A,
            B => Q_B,
            op => op,
            result => t_R
        );
    
    process(t_R, Q_R, clk)
    begin
        if ( t_R /= Q_R ) then
            t_done <= '1';
        else 
            t_done <= '0';
        end if;
    end process;
end behavior;

testbench/tb_Core.vhd
library ieee;
use IEEE.std_logic_1164.all;
use IEEE.numeric_std.all;
use IEEE.std_logic_unsigned.all;

entity tb_Core is
end tb_Core;

architecture behavior of tb_Core is
    component Core is
        port(
            dataIn : in std_logic_vector(63 downto 0);
            clk : in std_logic;
            load : in std_logic;
            op : in std_logic_vector(1 downto 0);
            dataOut : out std_logic_vector(31 downto 0);
            isDone : out std_logic
        );
    end component;
signal t_dataIn_0, t_dataIn_1, t_dataOut : std_logic_vector(31 downto 0);
signal t_clk, t_load, t_isDone : std_logic;
signal t_op : std_logic_vector(1 downto 0) := "00";
signal t_dataIn : std_logic_vector(63 downto 0);
begin 
    t_dataIn <= t_dataIn_0 & t_dataIn_1;
    tbCore : Core
        port map(
            dataIn => t_dataIn,
            clk => t_clk,
            load => t_load,
            op => t_op,
            dataOut => t_dataOut,
            isDone => t_isDone
        );
    process
    begin
        t_clk <= '0';
        wait for 1 ns;
        t_clk <= '1';
        wait for 1 ns;
    end process;

    process
    begin
        wait for 20 ns;
        t_op <= t_op + 1;
        wait for 20 ns;
    end process;

    process
    begin
        t_load <= '0';
        wait for 10 ns;
        t_load <= '1';
        wait for 10 ns;
    end process;

    process
    begin
        t_dataIn_0 <= X"13AE147A"; --1.23
        t_dataIn_1 <= X"01C8C932"; --0.11152
        wait for 40 ns;
        t_dataIn_0 <= X"00333333"; --0.0125
        t_dataIn_1 <= X"1067A0F9"; --1.0253
        wait for 40 ns;
    end process;
end behavior;

simulation/tb_Core.vcd
$date
  Sun Jun 21 20:06:27 2020
$end
$version
  GHDL v0
$end
$timescale
  1 fs
$end
$scope module standard $end
$upscope $end
$scope module std_logic_1164 $end
$upscope $end
$scope module numeric_std $end
$upscope $end
$scope module std_logic_arith $end
$upscope $end
$scope module std_logic_unsigned $end
$upscope $end
$scope module fixedpt $end
$upscope $end
$scope module tb_core $end
$var reg 32 ! t_datain_0[31:0] $end
$var reg 32 " t_datain_1[31:0] $end
$var reg 32 # t_dataout[31:0] $end
$var reg 1 $ t_clk $end
$var reg 1 % t_load $end
$var reg 1 & t_isdone $end
$var reg 2 ' t_op[1:0] $end
$var reg 64 ( t_datain[63:0] $end
$scope module tbcore $end
$var reg 64 ) datain[63:0] $end
$var reg 1 * clk $end
$var reg 1 + load $end
$var reg 2 , op[1:0] $end
$var reg 32 - dataout[31:0] $end
$var reg 1 . isdone $end
$var reg 32 / t_a[31:0] $end
$var reg 32 0 t_b[31:0] $end
$var reg 32 1 t_r[31:0] $end
$var reg 32 2 q_a[31:0] $end
$var reg 32 3 q_b[31:0] $end
$var reg 32 4 q_r[31:0] $end
$var reg 1 5 t_done $end
$scope module dff_a $end
$var reg 32 6 d[31:0] $end
$var reg 1 7 enable $end
$var reg 1 8 clk $end
$var reg 32 9 q[31:0] $end
$var reg 32 : q_out[31:0] $end
$var reg 32 ; d_in[31:0] $end
$var reg 32 < enable_32bit[31:0] $end
$upscope $end
$scope module dff_b $end
$var reg 32 = d[31:0] $end
$var reg 1 > enable $end
$var reg 1 ? clk $end
$var reg 32 @ q[31:0] $end
$var reg 32 A q_out[31:0] $end
$var reg 32 B d_in[31:0] $end
$var reg 32 C enable_32bit[31:0] $end
$upscope $end
$scope module dff_r $end
$var reg 32 D d[31:0] $end
$var reg 1 E enable $end
$var reg 1 F clk $end
$var reg 32 G q[31:0] $end
$var reg 32 H q_out[31:0] $end
$var reg 32 I d_in[31:0] $end
$var reg 32 J enable_32bit[31:0] $end
$upscope $end
$scope module fpucore $end
$var reg 32 K a[31:0] $end
$var reg 32 L b[31:0] $end
$var reg 2 M op[1:0] $end
$var reg 32 N result[31:0] $end
$var reg 32 O t_a[31:0] $end
$var reg 32 P t_b[31:0] $end
$var reg 32 Q t_result_add[31:0] $end
$var reg 32 R t_result_sub[31:0] $end
$var reg 32 S t_result_div[31:0] $end
$var reg 32 T t_result_mul[31:0] $end
$var reg 4 U t_sel[3:0] $end
$scope module add $end
$var reg 32 V a[31:0] $end
$var reg 32 W b[31:0] $end
$var reg 1 X sel $end
$var reg 32 Y result[31:0] $end
$var reg 32 Z t_result[31:0] $end
$upscope $end
$scope module sub $end
$var reg 32 [ a[31:0] $end
$var reg 32 \ b[31:0] $end
$var reg 1 ] sel $end
$var reg 32 ^ result[31:0] $end
$var reg 32 _ t_result[31:0] $end
$upscope $end
$scope module mul $end
$var reg 32 ` a[31:0] $end
$var reg 32 a b[31:0] $end
$var reg 1 b sel $end
$var reg 32 c result[31:0] $end
$var reg 64 d t_result[63:0] $end
$var reg 64 e t_mul[63:0] $end
$upscope $end
$scope module div $end
$var reg 32 f a[31:0] $end
$var reg 32 g b[31:0] $end
$var reg 1 h sel $end
$var reg 32 i result[31:0] $end
$var reg 64 j t_a[63:0] $end
$var reg 64 k t_b[63:0] $end
$var reg 64 l t_div[63:0] $end
$var reg 64 m t_result[63:0] $end
$upscope $end
$upscope $end
$upscope $end
$upscope $end
$enddefinitions $end
#0
b00010011101011100001010001111010 !
b00000001110010001100100100110010 "
bXXXXXXXXXXXXXXXXXXXXXXXXXXXXXXXX #
0$
0%
1&
b00 '
b0001001110101110000101000111101000000001110010001100100100110010 (
b0001001110101110000101000111101000000001110010001100100100110010 )
0*
0+
b00 ,
bXXXXXXXXXXXXXXXXXXXXXXXXXXXXXXXX -
1.
b00000001110010001100100100110010 /
b00010011101011100001010001111010 0
bXXXXXXXXXXXXXXXXXXXXXXXXXXXXXXXX 1
bUUUUUUUUUUUUUUUUUUUUUUUUUUUUUUUU 2
bUUUUUUUUUUUUUUUUUUUUUUUUUUUUUUUU 3
bUUUUUUUUUUUUUUUUUUUUUUUUUUUUUUUU 4
15
b00000001110010001100100100110010 6
07
08
bUUUUUUUUUUUUUUUUUUUUUUUUUUUUUUUU 9
bUUUUUUUUUUUUUUUUUUUUUUUUUUUUUUUU :
bUUUUUUUUUUUUUUUUUUUUUUUUUUUUUUUU ;
b00000000000000000000000000000000 <
b00010011101011100001010001111010 =
0>
0?
bUUUUUUUUUUUUUUUUUUUUUUUUUUUUUUUU @
bUUUUUUUUUUUUUUUUUUUUUUUUUUUUUUUU A
bUUUUUUUUUUUUUUUUUUUUUUUUUUUUUUUU B
b00000000000000000000000000000000 C
bXXXXXXXXXXXXXXXXXXXXXXXXXXXXXXXX D
0E
0F
bUUUUUUUUUUUUUUUUUUUUUUUUUUUUUUUU G
bUUUUUUUUUUUUUUUUUUUUUUUUUUUUUUUU H
bUUUUUUUUUUUUUUUUUUUUUUUUUUUUUUUU I
b00000000000000000000000000000000 J
bUUUUUUUUUUUUUUUUUUUUUUUUUUUUUUUU K
bUUUUUUUUUUUUUUUUUUUUUUUUUUUUUUUU L
b00 M
bXXXXXXXXXXXXXXXXXXXXXXXXXXXXXXXX N
bUUUUUUUUUUUUUUUUUUUUUUUUUUUUUUUU O
bUUUUUUUUUUUUUUUUUUUUUUUUUUUUUUUU P
bXXXXXXXXXXXXXXXXXXXXXXXXXXXXXXXX Q
bZZZZZZZZZZZZZZZZZZZZZZZZZZZZZZZZ R
bZZZZZZZZZZZZZZZZZZZZZZZZZZZZZZZZ S
bZZZZZZZZZZZZZZZZZZZZZZZZZZZZZZZZ T
b1110 U
bUUUUUUUUUUUUUUUUUUUUUUUUUUUUUUUU V
bUUUUUUUUUUUUUUUUUUUUUUUUUUUUUUUU W
0X
bXXXXXXXXXXXXXXXXXXXXXXXXXXXXXXXX Y
bXXXXXXXXXXXXXXXXXXXXXXXXXXXXXXXX Z
bUUUUUUUUUUUUUUUUUUUUUUUUUUUUUUUU [
bUUUUUUUUUUUUUUUUUUUUUUUUUUUUUUUU \
1]
bZZZZZZZZZZZZZZZZZZZZZZZZZZZZZZZZ ^
bZZZZZZZZZZZZZZZZZZZZZZZZZZZZZZZZ _
bUUUUUUUUUUUUUUUUUUUUUUUUUUUUUUUU `
bUUUUUUUUUUUUUUUUUUUUUUUUUUUUUUUU a
1b
bZZZZZZZZZZZZZZZZZZZZZZZZZZZZZZZZ c
bZZZZZZZZZZZZZZZZZZZZZZZZZZZZZZZZZZZZZZZZZZZZZZZZZZZZZZZZZZZZZZZZ d
bZZZZZZZZZZZZZZZZZZZZZZZZZZZZZZZZZZZZZZZZZZZZZZZZZZZZZZZZZZZZZZZZ e
bUUUUUUUUUUUUUUUUUUUUUUUUUUUUUUUU f
bUUUUUUUUUUUUUUUUUUUUUUUUUUUUUUUU g
1h
bZZZZZZZZZZZZZZZZZZZZZZZZZZZZZZZZ i
bZZZZZZZZZZZZZZZZZZZZZZZZZZZZZZZZZZZZZZZZZZZZZZZZZZZZZZZZZZZZZZZZ j
bZZZZZZZZZZZZZZZZZZZZZZZZZZZZZZZZZZZZZZZZZZZZZZZZZZZZZZZZZZZZZZZZ k
bZZZZZZZZZZZZZZZZZZZZZZZZZZZZZZZZZZZZZZZZZZZZZZZZZZZZZZZZZZZZZZZZ l
bUUUUUUUUUUUUUUUUUUUUUUUUUUUUUUUUUUUUUUUUUUUUUUUUUUUUUUUUUUUUUUUU m
#1000000
1$
1*
18
1?
1F
#2000000
0$
0*
08
0?
0F
#3000000
1$
1*
18
1?
1F
#4000000
0$
0*
08
0?
0F
#5000000
1$
1*
18
1?
1F
#6000000
0$
0*
08
0?
0F
#7000000
1$
1*
18
1?
1F
#8000000
0$
0*
08
0?
0F
#9000000
1$
1*
18
1?
1F
#10000000
0$
1%
0*
1+
17
08
b00000001110010001100100100110010 ;
b11111111111111111111111111111111 <
1>
0?
b00010011101011100001010001111010 B
b11111111111111111111111111111111 C
1E
0F
bXXXXXXXXXXXXXXXXXXXXXXXXXXXXXXXX I
b11111111111111111111111111111111 J
#11000000
b00010101011101101101110110101100 #
1$
1&
1*
b00010101011101101101110110101100 -
1.
b00010101011101101101110110101100 1
b00000001110010001100100100110010 2
b00010011101011100001010001111010 3
bXXXXXXXXXXXXXXXXXXXXXXXXXXXXXXXX 4
15
18
b00000001110010001100100100110010 9
b00000001110010001100100100110010 :
1?
b00010011101011100001010001111010 @
b00010011101011100001010001111010 A
b00010101011101101101110110101100 D
1F
bXXXXXXXXXXXXXXXXXXXXXXXXXXXXXXXX G
bXXXXXXXXXXXXXXXXXXXXXXXXXXXXXXXX H
b00010101011101101101110110101100 I
b00000001110010001100100100110010 K
b00010011101011100001010001111010 L
b00010101011101101101110110101100 N
b00000001110010001100100100110010 O
b00010011101011100001010001111010 P
b00010101011101101101110110101100 Q
b00000001110010001100100100110010 V
b00010011101011100001010001111010 W
b00010101011101101101110110101100 Y
b00010101011101101101110110101100 Z
b00000001110010001100100100110010 [
b00010011101011100001010001111010 \
b00000001110010001100100100110010 `
b00010011101011100001010001111010 a
b00000001110010001100100100110010 f
b00010011101011100001010001111010 g
#12000000
0$
0*
08
0?
0F
#13000000
1$
0&
1*
0.
b00010101011101101101110110101100 4
05
18
1?
1F
b00010101011101101101110110101100 G
b00010101011101101101110110101100 H
#14000000
0$
0*
08
0?
0F
#15000000
1$
1*
18
1?
1F
#16000000
0$
0*
08
0?
0F
#17000000
1$
1*
18
1?
1F
#18000000
0$
0*
08
0?
0F
#19000000
1$
1*
18
1?
1F
#20000000
b11101110000110101011010010111000 #
0$
0%
1&
b01 '
0*
0+
b01 ,
b11101110000110101011010010111000 -
1.
b11101110000110101011010010111000 1
15
07
08
b00000000000000000000000000000000 <
0>
0?
b00000000000000000000000000000000 C
b11101110000110101011010010111000 D
0E
0F
b00000000000000000000000000000000 J
b01 M
b11101110000110101011010010111000 N
bZZZZZZZZZZZZZZZZZZZZZZZZZZZZZZZZ Q
b11101110000110101011010010111000 R
b1101 U
1X
bZZZZZZZZZZZZZZZZZZZZZZZZZZZZZZZZ Y
bZZZZZZZZZZZZZZZZZZZZZZZZZZZZZZZZ Z
0]
b11101110000110101011010010111000 ^
b11101110000110101011010010111000 _
#21000000
1$
1*
18
1?
1F
#22000000
0$
0*
08
0?
0F
#23000000
1$
1*
18
1?
1F
#24000000
0$
0*
08
0?
0F
#25000000
1$
1*
18
1?
1F
#26000000
0$
0*
08
0?
0F
#27000000
1$
1*
18
1?
1F
#28000000
0$
0*
08
0?
0F
#29000000
1$
1*
18
1?
1F
#30000000
0$
1%
0*
1+
17
08
b11111111111111111111111111111111 <
1>
0?
b11111111111111111111111111111111 C
1E
0F
b11101110000110101011010010111000 I
b11111111111111111111111111111111 J
#31000000
1$
0&
1*
0.
b11101110000110101011010010111000 4
05
18
1?
1F
b11101110000110101011010010111000 G
b11101110000110101011010010111000 H
#32000000
0$
0*
08
0?
0F
#33000000
1$
1*
18
1?
1F
#34000000
0$
0*
08
0?
0F
#35000000
1$
1*
18
1?
1F
#36000000
0$
0*
08
0?
0F
#37000000
1$
1*
18
1?
1F
#38000000
0$
0*
08
0?
0F
#39000000
1$
1*
18
1?
1F
#40000000
b00000000001100110011001100110011 !
b00010000011001111010000011111001 "
0$
0%
b0000000000110011001100110011001100010000011001111010000011111001 (
b0000000000110011001100110011001100010000011001111010000011111001 )
0*
0+
b00010000011001111010000011111001 /
b00000000001100110011001100110011 0
b00010000011001111010000011111001 6
07
08
b00000000000000000000000000000000 <
b00000000001100110011001100110011 =
0>
0?
b00000000000000000000000000000000 C
0E
0F
b00000000000000000000000000000000 J
#41000000
1$
1*
18
1?
1F
#42000000
0$
0*
08
0?
0F
#43000000
1$
1*
18
1?
1F
#44000000
0$
0*
08
0?
0F
#45000000
1$
1*
18
1?
1F
#46000000
0$
0*
08
0?
0F
#47000000
1$
1*
18
1?
1F
#48000000
0$
0*
08
0?
0F
#49000000
1$
1*
18
1?
1F
#50000000
0$
1%
0*
1+
17
08
b00010000011001111010000011111001 ;
b11111111111111111111111111111111 <
1>
0?
b00000000001100110011001100110011 B
b11111111111111111111111111111111 C
1E
0F
b11111111111111111111111111111111 J
#51000000
b00010000001101000110110111000110 #
1$
1&
1*
b00010000001101000110110111000110 -
1.
b00010000001101000110110111000110 1
b00010000011001111010000011111001 2
b00000000001100110011001100110011 3
15
18
b00010000011001111010000011111001 9
b00010000011001111010000011111001 :
1?
b00000000001100110011001100110011 @
b00000000001100110011001100110011 A
b00010000001101000110110111000110 D
1F
b00010000001101000110110111000110 I
b00010000011001111010000011111001 K
b00000000001100110011001100110011 L
b00010000001101000110110111000110 N
b00010000011001111010000011111001 O
b00000000001100110011001100110011 P
b00010000001101000110110111000110 R
b00010000011001111010000011111001 V
b00000000001100110011001100110011 W
b00010000011001111010000011111001 [
b00000000001100110011001100110011 \
b00010000001101000110110111000110 ^
b00010000001101000110110111000110 _
b00010000011001111010000011111001 `
b00000000001100110011001100110011 a
b00010000011001111010000011111001 f
b00000000001100110011001100110011 g
#52000000
0$
0*
08
0?
0F
#53000000
1$
0&
1*
0.
b00010000001101000110110111000110 4
05
18
1?
1F
b00010000001101000110110111000110 G
b00010000001101000110110111000110 H
#54000000
0$
0*
08
0?
0F
#55000000
1$
1*
18
1?
1F
#56000000
0$
0*
08
0?
0F
#57000000
1$
1*
18
1?
1F
#58000000
0$
0*
08
0?
0F
#59000000
1$
1*
18
1?
1F
#60000000
b00000000001101000111111011001111 #
0$
0%
1&
b10 '
0*
0+
b10 ,
b00000000001101000111111011001111 -
1.
b00000000001101000111111011001111 1
15
07
08
b00000000000000000000000000000000 <
0>
0?
b00000000000000000000000000000000 C
b00000000001101000111111011001111 D
0E
0F
b00000000000000000000000000000000 J
b10 M
b00000000001101000111111011001111 N
bZZZZZZZZZZZZZZZZZZZZZZZZZZZZZZZZ R
b00000000001101000111111011001111 T
b1011 U
1]
bZZZZZZZZZZZZZZZZZZZZZZZZZZZZZZZZ ^
bZZZZZZZZZZZZZZZZZZZZZZZZZZZZZZZZ _
0b
b00000000001101000111111011001111 c
b0000000000000000000000000000000000000000001101000111111011001111 d
b0000000000000011010001111110110011111011010100011010110010011011 e
#61000000
1$
1*
18
1?
1F
#62000000
0$
0*
08
0?
0F
#63000000
1$
1*
18
1?
1F
#64000000
0$
0*
08
0?
0F
#65000000
1$
1*
18
1?
1F
#66000000
0$
0*
08
0?
0F
#67000000
1$
1*
18
1?
1F
#68000000
0$
0*
08
0?
0F
#69000000
1$
1*
18
1?
1F
#70000000
0$
1%
0*
1+
17
08
b11111111111111111111111111111111 <
1>
0?
b11111111111111111111111111111111 C
1E
0F
b00000000001101000111111011001111 I
b11111111111111111111111111111111 J
#71000000
1$
0&
1*
0.
b00000000001101000111111011001111 4
05
18
1?
1F
b00000000001101000111111011001111 G
b00000000001101000111111011001111 H
#72000000
0$
0*
08
0?
0F
#73000000
1$
1*
18
1?
1F
#74000000
0$
0*
08
0?
0F
#75000000
1$
1*
18
1?
1F
#76000000
0$
0*
08
0?
0F
#77000000
1$
1*
18
1?
1F
#78000000
0$
0*
08
0?
0F
#79000000
1$
1*
18
1?
1F
#80000000
b00010011101011100001010001111010 !
b00000001110010001100100100110010 "
0$
0%
b0001001110101110000101000111101000000001110010001100100100110010 (
b0001001110101110000101000111101000000001110010001100100100110010 )
0*
0+
b00000001110010001100100100110010 /
b00010011101011100001010001111010 0
b00000001110010001100100100110010 6
07
08
b00000000000000000000000000000000 <
b00010011101011100001010001111010 =
0>
0?
b00000000000000000000000000000000 C
0E
0F
b00000000000000000000000000000000 J
#81000000
1$
1*
18
1?
1F
#82000000
0$
0*
08
0?
0F
#83000000
1$
1*
18
1?
1F
#84000000
0$
0*
08
0?
0F
#85000000
1$
1*
18
1?
1F
#86000000
0$
0*
08
0?
0F
#87000000
1$
1*
18
1?
1F
#88000000
0$
0*
08
0?
0F
#89000000
1$
1*
18
1?
1F
#90000000
0$
1%
0*
1+
17
08
b00000001110010001100100100110010 ;
b11111111111111111111111111111111 <
1>
0?
b00010011101011100001010001111010 B
b11111111111111111111111111111111 C
1E
0F
b11111111111111111111111111111111 J
#91000000
b00000010001100011101100010111111 #
1$
1&
1*
b00000010001100011101100010111111 -
1.
b00000010001100011101100010111111 1
b00000001110010001100100100110010 2
b00010011101011100001010001111010 3
15
18
b00000001110010001100100100110010 9
b00000001110010001100100100110010 :
1?
b00010011101011100001010001111010 @
b00010011101011100001010001111010 A
b00000010001100011101100010111111 D
1F
b00000010001100011101100010111111 I
b00000001110010001100100100110010 K
b00010011101011100001010001111010 L
b00000010001100011101100010111111 N
b00000001110010001100100100110010 O
b00010011101011100001010001111010 P
b00000010001100011101100010111111 T
b00000001110010001100100100110010 V
b00010011101011100001010001111010 W
b00000001110010001100100100110010 [
b00010011101011100001010001111010 \
b00000001110010001100100100110010 `
b00010011101011100001010001111010 a
b00000010001100011101100010111111 c
b0000000000000000000000000000000000000010001100011101100010111111 d
b0000000000100011000111011000101111111111011000111100100111010100 e
b00000001110010001100100100110010 f
b00010011101011100001010001111010 g
#92000000
0$
0*
08
0?
0F
#93000000
1$
0&
1*
0.
b00000010001100011101100010111111 4
05
18
1?
1F
b00000010001100011101100010111111 G
b00000010001100011101100010111111 H
#94000000
0$
0*
08
0?
0F
#95000000
1$
1*
18
1?
1F
#96000000
0$
0*
08
0?
0F
#97000000
1$
1*
18
1?
1F
#98000000
0$
0*
08
0?
0F
#99000000
1$
1*
18
1?
1F
#100000000
b00000001011100110101111011100100 #
0$
0%
1&
b11 '
0*
0+
b11 ,
b00000001011100110101111011100100 -
1.
b00000001011100110101111011100100 1
15
07
08
b00000000000000000000000000000000 <
0>
0?
b00000000000000000000000000000000 C
b00000001011100110101111011100100 D
0E
0F
b00000000000000000000000000000000 J
b11 M
b00000001011100110101111011100100 N
b00000001011100110101111011100100 S
bZZZZZZZZZZZZZZZZZZZZZZZZZZZZZZZZ T
b0111 U
1b
bZZZZZZZZZZZZZZZZZZZZZZZZZZZZZZZZ c
bZZZZZZZZZZZZZZZZZZZZZZZZZZZZZZZZZZZZZZZZZZZZZZZZZZZZZZZZZZZZZZZZ d
bZZZZZZZZZZZZZZZZZZZZZZZZZZZZZZZZZZZZZZZZZZZZZZZZZZZZZZZZZZZZZZZZ e
0h
b00000001011100110101111011100100 i
b0000000000011100100011001001001100100000000000000000000000000000 j
b0000000000000000000000000000000000010011101011100001010001111010 k
b0000000000000000000000000000000000000001011100110101111011100100 l
#101000000
1$
1*
18
1?
1F
#102000000
0$
0*
08
0?
0F
#103000000
1$
1*
18
1?
1F
#104000000
0$
0*
08
0?
0F
#105000000
1$
1*
18
1?
1F
#106000000
0$
0*
08
0?
0F
#107000000
1$
1*
18
1?
1F
#108000000
0$
0*
08
0?
0F
#109000000
1$
1*
18
1?
1F
#110000000
0$
1%
0*
1+
17
08
b11111111111111111111111111111111 <
1>
0?
b11111111111111111111111111111111 C
1E
0F
b00000001011100110101111011100100 I
b11111111111111111111111111111111 J
#111000000
1$
0&
1*
0.
b00000001011100110101111011100100 4
05
18
1?
1F
b00000001011100110101111011100100 G
b00000001011100110101111011100100 H
#112000000
0$
0*
08
0?
0F
#113000000
1$
1*
18
1?
1F
#114000000
0$
0*
08
0?
0F
#115000000
1$
1*
18
1?
1F
#116000000
0$
0*
08
0?
0F
#117000000
1$
1*
18
1?
1F
#118000000
0$
0*
08
0?
0F
#119000000
1$
1*
18
1?
1F
#120000000
b00000000001100110011001100110011 !
b00010000011001111010000011111001 "
0$
0%
b0000000000110011001100110011001100010000011001111010000011111001 (
b0000000000110011001100110011001100010000011001111010000011111001 )
0*
0+
b00010000011001111010000011111001 /
b00000000001100110011001100110011 0
b00010000011001111010000011111001 6
07
08
b00000000000000000000000000000000 <
b00000000001100110011001100110011 =
0>
0?
b00000000000000000000000000000000 C
0E
0F
b00000000000000000000000000000000 J
